{"intent_id":"5242cd89-4aed-4141-a427-8ed21f3ef750","service_type":"mMTC","sla_requirements":{"service_type":"mMTC","device_density":1000,"latency_max_ms":200,"availability_target":97.0},"ml_prediction":{"risk_score":0.7640536836098126,"risk_level":"high","viability_score":null,"confidence":0.85,"timestamp":"2025-12-24T00:40:43.253606+00:00","model_used":false,"metrics_used":{"real_metrics_count":0,"real_metrics":[],"time_range_minutes":10}},"decision":"RENEG","justification":"Rule rule-002 matched: sla_compliance < 0.9","reason":"Rule rule-002 matched: sla_compliance < 0.9","blockchain_tx_hash":null,"tx_hash":null,"sla_hash":null,"timestamp":"2025-12-24T00:40:43.310458+00:00","status":"RENEGOTIATION_REQUIRED","sla_id":"dec-5242cd89-4aed-4141-a427-8ed21f3ef750","nest_id":"nest-5242cd89-4aed-4141-a427-8ed21f3ef750","sem_csmf_status":"OK","ml_nsmf_status":"OK","bc_status":"SKIPPED","sla_agent_status":"SKIPPED","block_number":null}
