{"intent_id":"04540871-aaa1-4f5c-8b03-205411ecea5b","service_type":"URLLC","sla_requirements":{"service_type":"URLLC","latency_max_ms":20,"reliability_target":99.8,"jitter_max_ms":6},"ml_prediction":{"risk_score":0.7423461910152553,"risk_level":"high","viability_score":null,"confidence":0.85,"timestamp":"2025-12-24T00:40:37.683099+00:00","model_used":false,"metrics_used":{"real_metrics_count":0,"real_metrics":[],"time_range_minutes":10}},"decision":"RENEG","justification":"Rule rule-002 matched: sla_compliance < 0.9","reason":"Rule rule-002 matched: sla_compliance < 0.9","blockchain_tx_hash":null,"tx_hash":null,"sla_hash":null,"timestamp":"2025-12-24T00:40:37.702029+00:00","status":"RENEGOTIATION_REQUIRED","sla_id":"dec-04540871-aaa1-4f5c-8b03-205411ecea5b","nest_id":"nest-04540871-aaa1-4f5c-8b03-205411ecea5b","sem_csmf_status":"OK","ml_nsmf_status":"OK","bc_status":"SKIPPED","sla_agent_status":"SKIPPED","block_number":null}
